README.md
setup.cfg
setup.py
dsemu/__init__.py
dsemu.egg-info/PKG-INFO
dsemu.egg-info/SOURCES.txt
dsemu.egg-info/dependency_links.txt
dsemu.egg-info/top_level.txt