Metadata-Version: 2.1
Name: dsemu
Version: 0.2.1
Summary: A wrapper around the datastore emulator instance for use in tests.
Home-page: https://github.com/fwojciec/dsemu
Author: Filip Wojciechowski
Author-email: fwojciec@gmail.com
License: MIT
Platform: UNKNOWN
Classifier: Development Status :: 2 - Pre-Alpha
Classifier: License :: OSI Approved :: MIT License
Classifier: Programming Language :: Python
Classifier: Programming Language :: Python :: 3.7
